{
  "fio version" : "fio-3.1",
  "timestamp" : 1574248594,
  "timestamp_ms" : 1574248594922,
  "time" : "Wed Nov 20 11:16:34 2019",
  "global options" : {
    "directory" : "data/fio_read",
    "bs" : "256",
    "fallocate" : "none",
    "runtime" : "30",
    "time_based" : "1",
    "ioengine" : "libaio",
    "iodepth" : "8",
    "direct" : "1",
    "buffered" : "0",
    "invalidate" : "1",
    "ramp_time" : "0",
    "thread" : "0",
    "group_reporting" : "1",
    "filesize" : "32g",
    "size" : "32g",
    "filename_format" : "$jobnum.dat"
  },
  "jobs" : [
    {
      "jobname" : "fio-job",
      "groupid" : 0,
      "error" : 0,
      "eta" : 0,
      "elapsed" : 31,
      "job options" : {
        "rw" : "read"
      },
      "read" : {
        "io_bytes" : 2678352384,
        "io_kbytes" : 2615578,
        "bw" : 87177,
        "iops" : 348708.929107,
        "runtime" : 30003,
        "total_ios" : 10462314,
        "short_ios" : 0,
        "drop_ios" : 0,
        "slat_ns" : {
          "min" : 947,
          "max" : 14069905,
          "mean" : 6984.600153,
          "stddev" : 162278.249062
        },
        "clat_ns" : {
          "min" : 1576,
          "max" : 14087590,
          "mean" : 82763.888120,
          "stddev" : 554640.631535,
          "percentile" : {
            "1.000000" : 14400,
            "5.000000" : 14656,
            "10.000000" : 14912,
            "20.000000" : 15296,
            "30.000000" : 15808,
            "40.000000" : 19072,
            "50.000000" : 19840,
            "60.000000" : 20352,
            "70.000000" : 21120,
            "80.000000" : 22656,
            "90.000000" : 28800,
            "95.000000" : 30336,
            "99.000000" : 3948544,
            "99.500000" : 5079040,
            "99.900000" : 6062080,
            "99.950000" : 7045120,
            "99.990000" : 8978432,
            "0.00" : 0,
            "0.00" : 0,
            "0.00" : 0
          },
          "bins" : {
            "1576" : 1,
            "2448" : 1,
            "2608" : 1,
            "3600" : 1,
            "3632" : 1,
            "5600" : 1,
            "7584" : 1,
            "9664" : 1,
            "11584" : 1,
            "12736" : 108,
            "12864" : 36,
            "12992" : 86,
            "13120" : 74,
            "13248" : 58,
            "13376" : 29,
            "13504" : 78,
            "13632" : 596,
            "13760" : 1738,
            "13888" : 5310,
            "14016" : 10411,
            "14144" : 8701,
            "14272" : 15530,
            "14400" : 64983,
            "14528" : 208028,
            "14656" : 306760,
            "14784" : 244075,
            "14912" : 257721,
            "15040" : 309265,
            "15168" : 390372,
            "15296" : 373472,
            "15424" : 327722,
            "15552" : 297694,
            "15680" : 291679,
            "15808" : 250689,
            "15936" : 167870,
            "16064" : 123298,
            "16192" : 92546,
            "16320" : 64715,
            "16512" : 69271,
            "16768" : 26892,
            "17024" : 10861,
            "17280" : 4638,
            "17536" : 2382,
            "17792" : 2170,
            "18048" : 2954,
            "18304" : 6143,
            "18560" : 18052,
            "18816" : 69876,
            "19072" : 187822,
            "19328" : 315710,
            "19584" : 404181,
            "19840" : 485871,
            "20096" : 508614,
            "20352" : 491797,
            "20608" : 406782,
            "20864" : 325129,
            "21120" : 271909,
            "21376" : 227036,
            "21632" : 193706,
            "21888" : 171979,
            "22144" : 148132,
            "22400" : 122286,
            "22656" : 98646,
            "22912" : 76750,
            "23168" : 59098,
            "23424" : 44688,
            "23680" : 33935,
            "23936" : 26210,
            "24192" : 20343,
            "24448" : 16069,
            "24704" : 12809,
            "24960" : 10314,
            "25216" : 8233,
            "25472" : 7022,
            "25728" : 6400,
            "25984" : 6465,
            "26240" : 7675,
            "26496" : 11457,
            "26752" : 20604,
            "27008" : 35519,
            "27264" : 55039,
            "27520" : 76908,
            "27776" : 97658,
            "28032" : 110728,
            "28288" : 120337,
            "28544" : 125094,
            "28800" : 125498,
            "29056" : 119145,
            "29312" : 104445,
            "29568" : 87665,
            "29824" : 69783,
            "30080" : 53517,
            "30336" : 40109,
            "30592" : 30570,
            "30848" : 23453,
            "31104" : 18580,
            "31360" : 15091,
            "31616" : 13083,
            "31872" : 11239,
            "32128" : 9568,
            "32384" : 8867,
            "32640" : 8233,
            "33024" : 14515,
            "33536" : 12980,
            "34048" : 11895,
            "34560" : 10386,
            "35072" : 8184,
            "35584" : 6505,
            "36096" : 5185,
            "36608" : 4220,
            "37120" : 3930,
            "37632" : 3680,
            "38144" : 3857,
            "38656" : 4600,
            "39168" : 5354,
            "39680" : 6086,
            "40192" : 6770,
            "40704" : 7038,
            "41216" : 6936,
            "41728" : 6055,
            "42240" : 5144,
            "42752" : 3776,
            "43264" : 2985,
            "43776" : 2194,
            "44288" : 1891,
            "44800" : 1560,
            "45312" : 1437,
            "45824" : 1333,
            "46336" : 1272,
            "46848" : 1101,
            "47360" : 992,
            "47872" : 896,
            "48384" : 857,
            "48896" : 821,
            "49408" : 732,
            "49920" : 633,
            "50432" : 580,
            "50944" : 575,
            "51456" : 626,
            "51968" : 637,
            "52480" : 646,
            "52992" : 635,
            "53504" : 571,
            "54016" : 555,
            "54528" : 578,
            "55040" : 492,
            "55552" : 542,
            "56064" : 468,
            "56576" : 467,
            "57088" : 400,
            "57600" : 348,
            "58112" : 326,
            "58624" : 275,
            "59136" : 238,
            "59648" : 227,
            "60160" : 218,
            "60672" : 207,
            "61184" : 160,
            "61696" : 197,
            "62208" : 216,
            "62720" : 166,
            "63232" : 214,
            "63744" : 182,
            "64256" : 241,
            "64768" : 241,
            "65280" : 239,
            "66048" : 437,
            "67072" : 499,
            "68096" : 393,
            "69120" : 314,
            "70144" : 301,
            "71168" : 313,
            "72192" : 322,
            "73216" : 328,
            "74240" : 271,
            "75264" : 249,
            "76288" : 228,
            "77312" : 202,
            "78336" : 171,
            "79360" : 156,
            "80384" : 174,
            "81408" : 158,
            "82432" : 192,
            "83456" : 132,
            "84480" : 167,
            "85504" : 156,
            "86528" : 161,
            "87552" : 146,
            "88576" : 193,
            "89600" : 183,
            "90624" : 208,
            "91648" : 236,
            "92672" : 152,
            "93696" : 178,
            "94720" : 168,
            "95744" : 189,
            "96768" : 229,
            "97792" : 212,
            "98816" : 155,
            "99840" : 225,
            "100864" : 212,
            "101888" : 191,
            "102912" : 166,
            "103936" : 187,
            "104960" : 160,
            "105984" : 157,
            "107008" : 148,
            "108032" : 150,
            "109056" : 164,
            "110080" : 200,
            "111104" : 192,
            "112128" : 184,
            "113152" : 200,
            "114176" : 165,
            "115200" : 170,
            "116224" : 156,
            "117248" : 157,
            "118272" : 120,
            "119296" : 142,
            "120320" : 135,
            "121344" : 161,
            "122368" : 121,
            "123392" : 158,
            "124416" : 137,
            "125440" : 153,
            "126464" : 122,
            "127488" : 162,
            "128512" : 168,
            "129536" : 164,
            "130560" : 189,
            "132096" : 267,
            "134144" : 254,
            "136192" : 301,
            "138240" : 312,
            "140288" : 337,
            "142336" : 289,
            "144384" : 310,
            "146432" : 242,
            "148480" : 206,
            "150528" : 279,
            "152576" : 231,
            "154624" : 236,
            "156672" : 219,
            "158720" : 199,
            "160768" : 229,
            "162816" : 181,
            "164864" : 164,
            "166912" : 166,
            "168960" : 214,
            "171008" : 142,
            "173056" : 140,
            "175104" : 108,
            "177152" : 111,
            "179200" : 143,
            "181248" : 86,
            "183296" : 97,
            "185344" : 86,
            "187392" : 80,
            "189440" : 79,
            "191488" : 93,
            "193536" : 66,
            "195584" : 52,
            "197632" : 56,
            "199680" : 48,
            "201728" : 43,
            "203776" : 65,
            "205824" : 68,
            "207872" : 75,
            "209920" : 39,
            "211968" : 56,
            "214016" : 23,
            "216064" : 29,
            "218112" : 47,
            "220160" : 57,
            "222208" : 25,
            "224256" : 55,
            "226304" : 43,
            "228352" : 46,
            "230400" : 47,
            "232448" : 41,
            "234496" : 77,
            "236544" : 23,
            "238592" : 29,
            "240640" : 54,
            "242688" : 48,
            "244736" : 67,
            "246784" : 39,
            "248832" : 31,
            "250880" : 52,
            "252928" : 55,
            "254976" : 26,
            "257024" : 52,
            "259072" : 57,
            "261120" : 51,
            "264192" : 111,
            "268288" : 81,
            "272384" : 111,
            "276480" : 178,
            "280576" : 113,
            "284672" : 104,
            "288768" : 133,
            "292864" : 177,
            "296960" : 173,
            "301056" : 141,
            "305152" : 165,
            "309248" : 134,
            "313344" : 132,
            "317440" : 97,
            "321536" : 182,
            "325632" : 212,
            "329728" : 154,
            "333824" : 209,
            "337920" : 170,
            "342016" : 136,
            "346112" : 159,
            "350208" : 127,
            "354304" : 140,
            "358400" : 112,
            "362496" : 159,
            "366592" : 116,
            "370688" : 161,
            "374784" : 74,
            "378880" : 116,
            "382976" : 102,
            "387072" : 98,
            "391168" : 89,
            "395264" : 91,
            "399360" : 81,
            "403456" : 80,
            "407552" : 53,
            "411648" : 65,
            "415744" : 61,
            "419840" : 96,
            "423936" : 86,
            "428032" : 79,
            "432128" : 82,
            "436224" : 49,
            "440320" : 79,
            "444416" : 112,
            "448512" : 54,
            "452608" : 71,
            "456704" : 47,
            "460800" : 98,
            "464896" : 64,
            "468992" : 32,
            "473088" : 45,
            "477184" : 60,
            "481280" : 53,
            "485376" : 65,
            "489472" : 74,
            "493568" : 60,
            "497664" : 77,
            "501760" : 81,
            "505856" : 56,
            "509952" : 59,
            "514048" : 78,
            "518144" : 45,
            "522240" : 52,
            "528384" : 131,
            "536576" : 75,
            "544768" : 135,
            "552960" : 132,
            "561152" : 87,
            "569344" : 95,
            "577536" : 130,
            "585728" : 119,
            "593920" : 129,
            "602112" : 129,
            "610304" : 143,
            "618496" : 148,
            "626688" : 151,
            "634880" : 182,
            "643072" : 131,
            "651264" : 152,
            "659456" : 162,
            "667648" : 118,
            "675840" : 119,
            "684032" : 143,
            "692224" : 128,
            "700416" : 163,
            "708608" : 167,
            "716800" : 110,
            "724992" : 121,
            "733184" : 111,
            "741376" : 165,
            "749568" : 159,
            "757760" : 205,
            "765952" : 121,
            "774144" : 186,
            "782336" : 137,
            "790528" : 124,
            "798720" : 149,
            "806912" : 141,
            "815104" : 126,
            "823296" : 152,
            "831488" : 141,
            "839680" : 114,
            "847872" : 180,
            "856064" : 152,
            "864256" : 137,
            "872448" : 98,
            "880640" : 105,
            "888832" : 144,
            "897024" : 154,
            "905216" : 151,
            "913408" : 104,
            "921600" : 71,
            "929792" : 101,
            "937984" : 128,
            "946176" : 131,
            "954368" : 133,
            "962560" : 181,
            "970752" : 110,
            "978944" : 104,
            "987136" : 63,
            "995328" : 66,
            "1003520" : 61,
            "1011712" : 66,
            "1019904" : 57,
            "1028096" : 565,
            "1036288" : 1970,
            "1044480" : 1223,
            "1056768" : 961,
            "1073152" : 175,
            "1089536" : 145,
            "1105920" : 110,
            "1122304" : 117,
            "1138688" : 146,
            "1155072" : 112,
            "1171456" : 68,
            "1187840" : 112,
            "1204224" : 94,
            "1220608" : 90,
            "1236992" : 73,
            "1253376" : 122,
            "1269760" : 98,
            "1286144" : 113,
            "1302528" : 102,
            "1318912" : 81,
            "1335296" : 114,
            "1351680" : 113,
            "1368064" : 81,
            "1384448" : 112,
            "1400832" : 136,
            "1417216" : 192,
            "1433600" : 135,
            "1449984" : 206,
            "1466368" : 303,
            "1482752" : 176,
            "1499136" : 186,
            "1515520" : 129,
            "1531904" : 153,
            "1548288" : 237,
            "1564672" : 182,
            "1581056" : 365,
            "1597440" : 239,
            "1613824" : 301,
            "1630208" : 280,
            "1646592" : 198,
            "1662976" : 190,
            "1679360" : 204,
            "1695744" : 165,
            "1712128" : 158,
            "1728512" : 207,
            "1744896" : 293,
            "1761280" : 200,
            "1777664" : 175,
            "1794048" : 103,
            "1810432" : 106,
            "1826816" : 141,
            "1843200" : 156,
            "1859584" : 146,
            "1875968" : 128,
            "1892352" : 195,
            "1908736" : 195,
            "1925120" : 132,
            "1941504" : 161,
            "1957888" : 147,
            "1974272" : 171,
            "1990656" : 113,
            "2007040" : 54,
            "2023424" : 432,
            "2039808" : 3792,
            "2056192" : 1396,
            "2072576" : 258,
            "2088960" : 224,
            "2113536" : 515,
            "2146304" : 441,
            "2179072" : 516,
            "2211840" : 611,
            "2244608" : 505,
            "2277376" : 592,
            "2310144" : 644,
            "2342912" : 515,
            "2375680" : 505,
            "2408448" : 497,
            "2441216" : 557,
            "2473984" : 357,
            "2506752" : 344,
            "2539520" : 361,
            "2572288" : 205,
            "2605056" : 248,
            "2637824" : 213,
            "2670592" : 258,
            "2703360" : 198,
            "2736128" : 184,
            "2768896" : 187,
            "2801664" : 160,
            "2834432" : 237,
            "2867200" : 122,
            "2899968" : 150,
            "2932736" : 124,
            "2965504" : 170,
            "2998272" : 144,
            "3031040" : 2952,
            "3063808" : 1069,
            "3096576" : 393,
            "3129344" : 406,
            "3162112" : 162,
            "3194880" : 118,
            "3227648" : 145,
            "3260416" : 160,
            "3293184" : 201,
            "3325952" : 252,
            "3358720" : 211,
            "3391488" : 232,
            "3424256" : 222,
            "3457024" : 216,
            "3489792" : 220,
            "3522560" : 247,
            "3555328" : 235,
            "3588096" : 312,
            "3620864" : 279,
            "3653632" : 244,
            "3686400" : 321,
            "3719168" : 400,
            "3751936" : 838,
            "3784704" : 638,
            "3817472" : 325,
            "3850240" : 331,
            "3883008" : 255,
            "3915776" : 289,
            "3948544" : 342,
            "3981312" : 405,
            "4014080" : 2542,
            "4046848" : 15977,
            "4079616" : 598,
            "4112384" : 534,
            "4145152" : 582,
            "4177920" : 417,
            "4227072" : 882,
            "4292608" : 827,
            "4358144" : 529,
            "4423680" : 698,
            "4489216" : 598,
            "4554752" : 483,
            "4620288" : 480,
            "4685824" : 1314,
            "4751360" : 432,
            "4816896" : 335,
            "4882432" : 340,
            "4947968" : 390,
            "5013504" : 20421,
            "5079040" : 6214,
            "5144576" : 674,
            "5210112" : 1032,
            "5275648" : 765,
            "5341184" : 1243,
            "5406720" : 974,
            "5472256" : 1271,
            "5537792" : 1153,
            "5603328" : 1836,
            "5668864" : 1425,
            "5734400" : 1035,
            "5799936" : 1273,
            "5865472" : 1107,
            "5931008" : 1131,
            "5996544" : 4327,
            "6062080" : 22859,
            "6127616" : 402,
            "6193152" : 272,
            "6258688" : 272,
            "6324224" : 119,
            "6389760" : 114,
            "6455296" : 154,
            "6520832" : 182,
            "6586368" : 148,
            "6651904" : 42,
            "6717440" : 56,
            "6782976" : 31,
            "6848512" : 65,
            "6914048" : 38,
            "6979584" : 28,
            "7045120" : 3243,
            "7110656" : 44,
            "7176192" : 33,
            "7241728" : 24,
            "7307264" : 33,
            "7372800" : 21,
            "7438336" : 7,
            "7503872" : 19,
            "7569408" : 14,
            "7634944" : 7,
            "7700480" : 15,
            "7831552" : 4,
            "7897088" : 3,
            "7962624" : 6,
            "8028160" : 520,
            "8093696" : 14,
            "8159232" : 10,
            "8224768" : 29,
            "8290304" : 44,
            "8355840" : 7,
            "8454144" : 37,
            "8585216" : 7,
            "8978432" : 507,
            "9109504" : 122,
            "9240576" : 7,
            "9371648" : 7,
            "9502720" : 7,
            "9633792" : 13,
            "10027008" : 274,
            "10158080" : 31,
            "10289152" : 14,
            "10813440" : 7,
            "11075584" : 133,
            "11993088" : 8,
            "12124160" : 7,
            "14090240" : 7
          }
        },
        "lat_ns" : {
          "min" : 2760,
          "max" : 14088854,
          "mean" : 90062.343804,
          "stddev" : 578362.656143
        },
        "bw_min" : 17038,
        "bw_max" : 25252,
        "bw_agg" : 25.040064,
        "bw_mean" : 21829.176471,
        "bw_dev" : 2510.349861,
        "bw_samples" : 238,
        "iops_min" : 68152,
        "iops_max" : 101010,
        "iops_mean" : 87317.831933,
        "iops_stddev" : 10041.482632,
        "iops_samples" : 238
      },
      "write" : {
        "io_bytes" : 0,
        "io_kbytes" : 0,
        "bw" : 0,
        "iops" : 0.000000,
        "runtime" : 0,
        "total_ios" : 0,
        "short_ios" : 0,
        "drop_ios" : 0,
        "slat_ns" : {
          "min" : 0,
          "max" : 0,
          "mean" : 0.000000,
          "stddev" : 0.000000
        },
        "clat_ns" : {
          "min" : 0,
          "max" : 0,
          "mean" : 0.000000,
          "stddev" : 0.000000,
          "percentile" : {
            "1.000000" : 0,
            "5.000000" : 0,
            "10.000000" : 0,
            "20.000000" : 0,
            "30.000000" : 0,
            "40.000000" : 0,
            "50.000000" : 0,
            "60.000000" : 0,
            "70.000000" : 0,
            "80.000000" : 0,
            "90.000000" : 0,
            "95.000000" : 0,
            "99.000000" : 0,
            "99.500000" : 0,
            "99.900000" : 0,
            "99.950000" : 0,
            "99.990000" : 0,
            "0.00" : 0,
            "0.00" : 0,
            "0.00" : 0
          },
          "bins" : {

          }
        },
        "lat_ns" : {
          "min" : 0,
          "max" : 0,
          "mean" : 0.000000,
          "stddev" : 0.000000
        },
        "bw_min" : 0,
        "bw_max" : 0,
        "bw_agg" : 0.000000,
        "bw_mean" : 0.000000,
        "bw_dev" : 0.000000,
        "bw_samples" : 0,
        "iops_min" : 0,
        "iops_max" : 0,
        "iops_mean" : 0.000000,
        "iops_stddev" : 0.000000,
        "iops_samples" : 0
      },
      "trim" : {
        "io_bytes" : 0,
        "io_kbytes" : 0,
        "bw" : 0,
        "iops" : 0.000000,
        "runtime" : 0,
        "total_ios" : 0,
        "short_ios" : 0,
        "drop_ios" : 0,
        "slat_ns" : {
          "min" : 0,
          "max" : 0,
          "mean" : 0.000000,
          "stddev" : 0.000000
        },
        "clat_ns" : {
          "min" : 0,
          "max" : 0,
          "mean" : 0.000000,
          "stddev" : 0.000000,
          "percentile" : {
            "1.000000" : 0,
            "5.000000" : 0,
            "10.000000" : 0,
            "20.000000" : 0,
            "30.000000" : 0,
            "40.000000" : 0,
            "50.000000" : 0,
            "60.000000" : 0,
            "70.000000" : 0,
            "80.000000" : 0,
            "90.000000" : 0,
            "95.000000" : 0,
            "99.000000" : 0,
            "99.500000" : 0,
            "99.900000" : 0,
            "99.950000" : 0,
            "99.990000" : 0,
            "0.00" : 0,
            "0.00" : 0,
            "0.00" : 0
          },
          "bins" : {

          }
        },
        "lat_ns" : {
          "min" : 0,
          "max" : 0,
          "mean" : 0.000000,
          "stddev" : 0.000000
        },
        "bw_min" : 0,
        "bw_max" : 0,
        "bw_agg" : 0.000000,
        "bw_mean" : 0.000000,
        "bw_dev" : 0.000000,
        "bw_samples" : 0,
        "iops_min" : 0,
        "iops_max" : 0,
        "iops_mean" : 0.000000,
        "iops_stddev" : 0.000000,
        "iops_samples" : 0
      },
      "usr_cpu" : 9.433176,
      "sys_cpu" : 15.370577,
      "ctx" : 27785,
      "majf" : 0,
      "minf" : 413,
      "iodepth_level" : {
        "1" : 0.100000,
        "2" : 0.100000,
        "4" : 0.100000,
        "8" : 99.999732,
        "16" : 0.000000,
        "32" : 0.000000,
        ">=64" : 0.000000
      },
      "latency_ns" : {
        "2" : 0.000000,
        "4" : 0.000000,
        "10" : 0.000000,
        "20" : 0.000000,
        "50" : 0.000000,
        "100" : 0.000000,
        "250" : 0.000000,
        "500" : 0.000000,
        "750" : 0.000000,
        "1000" : 0.000000
      },
      "latency_us" : {
        "2" : 0.010000,
        "4" : 0.010000,
        "10" : 0.010000,
        "20" : 52.408033,
        "50" : 45.756570,
        "100" : 0.185332,
        "250" : 0.115816,
        "500" : 0.061870,
        "750" : 0.038491,
        "1000" : 0.038108
      },
      "latency_ms" : {
        "2" : 0.133642,
        "4" : 0.269118,
        "10" : 0.988347,
        "20" : 0.010000,
        "50" : 0.000000,
        "100" : 0.000000,
        "250" : 0.000000,
        "500" : 0.000000,
        "750" : 0.000000,
        "1000" : 0.000000,
        "2000" : 0.000000,
        ">=2000" : 0.000000
      },
      "latency_depth" : 8,
      "latency_target" : 0,
      "latency_percentile" : 100.000000,
      "latency_window" : 0
    }
  ]
}
