{
  "fio version" : "fio-3.1",
  "timestamp" : 1574273656,
  "timestamp_ms" : 1574273656508,
  "time" : "Wed Nov 20 18:14:16 2019",
  "global options" : {
    "directory" : "data/fio_write/beegfs-write-64-xflbj",
    "bs" : "4096",
    "fallocate" : "none",
    "runtime" : "30",
    "time_based" : "1",
    "ioengine" : "libaio",
    "iodepth" : "8",
    "direct" : "1",
    "buffered" : "0",
    "invalidate" : "1",
    "ramp_time" : "0",
    "thread" : "0",
    "group_reporting" : "1",
    "filesize" : "32g",
    "size" : "32g",
    "filename_format" : "$jobnum.dat"
  },
  "jobs" : [
    {
      "jobname" : "fio-job",
      "groupid" : 0,
      "error" : 0,
      "eta" : 0,
      "elapsed" : 31,
      "job options" : {
        "rw" : "write"
      },
      "read" : {
        "io_bytes" : 0,
        "io_kbytes" : 0,
        "bw" : 0,
        "iops" : 0.000000,
        "runtime" : 0,
        "total_ios" : 0,
        "short_ios" : 0,
        "drop_ios" : 0,
        "slat_ns" : {
          "min" : 0,
          "max" : 0,
          "mean" : 0.000000,
          "stddev" : 0.000000
        },
        "clat_ns" : {
          "min" : 0,
          "max" : 0,
          "mean" : 0.000000,
          "stddev" : 0.000000,
          "percentile" : {
            "1.000000" : 0,
            "5.000000" : 0,
            "10.000000" : 0,
            "20.000000" : 0,
            "30.000000" : 0,
            "40.000000" : 0,
            "50.000000" : 0,
            "60.000000" : 0,
            "70.000000" : 0,
            "80.000000" : 0,
            "90.000000" : 0,
            "95.000000" : 0,
            "99.000000" : 0,
            "99.500000" : 0,
            "99.900000" : 0,
            "99.950000" : 0,
            "99.990000" : 0,
            "0.00" : 0,
            "0.00" : 0,
            "0.00" : 0
          },
          "bins" : {

          }
        },
        "lat_ns" : {
          "min" : 0,
          "max" : 0,
          "mean" : 0.000000,
          "stddev" : 0.000000
        },
        "bw_min" : 0,
        "bw_max" : 0,
        "bw_agg" : 0.000000,
        "bw_mean" : 0.000000,
        "bw_dev" : 0.000000,
        "bw_samples" : 0,
        "iops_min" : 0,
        "iops_max" : 0,
        "iops_mean" : 0.000000,
        "iops_stddev" : 0.000000,
        "iops_samples" : 0
      },
      "write" : {
        "io_bytes" : 1751474176,
        "io_kbytes" : 1710424,
        "bw" : 57012,
        "iops" : 14253.058231,
        "runtime" : 30001,
        "total_ios" : 427606,
        "short_ios" : 0,
        "drop_ios" : 0,
        "slat_ns" : {
          "min" : 24299,
          "max" : 1453194056,
          "mean" : 275448.697125,
          "stddev" : 5594536.612210
        },
        "clat_ns" : {
          "min" : 3347,
          "max" : 1454163956,
          "mean" : 1966098.700699,
          "stddev" : 14776414.594137,
          "percentile" : {
            "1.000000" : 428032,
            "5.000000" : 518144,
            "10.000000" : 585728,
            "20.000000" : 692224,
            "30.000000" : 790528,
            "40.000000" : 905216,
            "50.000000" : 1028096,
            "60.000000" : 1171456,
            "70.000000" : 1335296,
            "80.000000" : 1515520,
            "90.000000" : 1810432,
            "95.000000" : 2113536,
            "99.000000" : 5341184,
            "99.500000" : 45875200,
            "99.900000" : 223346688,
            "99.950000" : 312475648,
            "99.990000" : 488636416,
            "0.00" : 0,
            "0.00" : 0,
            "0.00" : 0
          },
          "bins" : {
            "3344" : 1,
            "3536" : 1,
            "4576" : 1,
            "4896" : 1,
            "284672" : 1,
            "296960" : 1,
            "305152" : 1,
            "309248" : 4,
            "313344" : 7,
            "317440" : 4,
            "321536" : 15,
            "325632" : 12,
            "329728" : 13,
            "333824" : 22,
            "337920" : 25,
            "342016" : 32,
            "346112" : 36,
            "350208" : 44,
            "354304" : 68,
            "358400" : 69,
            "362496" : 87,
            "366592" : 102,
            "370688" : 131,
            "374784" : 130,
            "378880" : 161,
            "382976" : 156,
            "387072" : 161,
            "391168" : 199,
            "395264" : 227,
            "399360" : 251,
            "403456" : 256,
            "407552" : 325,
            "411648" : 323,
            "415744" : 372,
            "419840" : 383,
            "423936" : 413,
            "428032" : 423,
            "432128" : 456,
            "436224" : 491,
            "440320" : 493,
            "444416" : 512,
            "448512" : 561,
            "452608" : 606,
            "456704" : 635,
            "460800" : 624,
            "464896" : 732,
            "468992" : 757,
            "473088" : 779,
            "477184" : 863,
            "481280" : 861,
            "485376" : 854,
            "489472" : 922,
            "493568" : 925,
            "497664" : 1032,
            "501760" : 1083,
            "505856" : 1037,
            "509952" : 1015,
            "514048" : 1056,
            "518144" : 1180,
            "522240" : 1187,
            "528384" : 2382,
            "536576" : 2467,
            "544768" : 2613,
            "552960" : 2642,
            "561152" : 2759,
            "569344" : 2799,
            "577536" : 2986,
            "585728" : 3137,
            "593920" : 3124,
            "602112" : 3171,
            "610304" : 3065,
            "618496" : 3350,
            "626688" : 3349,
            "634880" : 3311,
            "643072" : 3341,
            "651264" : 3370,
            "659456" : 3472,
            "667648" : 3499,
            "675840" : 3436,
            "684032" : 3390,
            "692224" : 3536,
            "700416" : 3384,
            "708608" : 3471,
            "716800" : 3469,
            "724992" : 3490,
            "733184" : 3540,
            "741376" : 3322,
            "749568" : 3479,
            "757760" : 3524,
            "765952" : 3398,
            "774144" : 3467,
            "782336" : 3389,
            "790528" : 3295,
            "798720" : 3352,
            "806912" : 3316,
            "815104" : 3248,
            "823296" : 3219,
            "831488" : 3139,
            "839680" : 3120,
            "847872" : 3262,
            "856064" : 3152,
            "864256" : 3062,
            "872448" : 3012,
            "880640" : 3035,
            "888832" : 2998,
            "897024" : 2871,
            "905216" : 2926,
            "913408" : 2874,
            "921600" : 2957,
            "929792" : 2778,
            "937984" : 2761,
            "946176" : 2779,
            "954368" : 2850,
            "962560" : 2704,
            "970752" : 2696,
            "978944" : 2729,
            "987136" : 2668,
            "995328" : 2757,
            "1003520" : 2691,
            "1011712" : 2660,
            "1019904" : 2592,
            "1028096" : 2637,
            "1036288" : 2524,
            "1044480" : 2429,
            "1056768" : 5187,
            "1073152" : 4924,
            "1089536" : 4870,
            "1105920" : 4850,
            "1122304" : 4845,
            "1138688" : 4704,
            "1155072" : 4658,
            "1171456" : 4624,
            "1187840" : 4518,
            "1204224" : 4750,
            "1220608" : 4633,
            "1236992" : 4584,
            "1253376" : 4576,
            "1269760" : 4526,
            "1286144" : 4395,
            "1302528" : 4205,
            "1318912" : 4288,
            "1335296" : 4295,
            "1351680" : 4154,
            "1368064" : 3908,
            "1384448" : 4016,
            "1400832" : 3976,
            "1417216" : 3877,
            "1433600" : 3672,
            "1449984" : 3550,
            "1466368" : 3437,
            "1482752" : 3332,
            "1499136" : 3254,
            "1515520" : 3109,
            "1531904" : 3065,
            "1548288" : 3079,
            "1564672" : 2945,
            "1581056" : 2935,
            "1597440" : 2720,
            "1613824" : 2587,
            "1630208" : 2680,
            "1646592" : 2512,
            "1662976" : 2436,
            "1679360" : 2264,
            "1695744" : 2242,
            "1712128" : 2149,
            "1728512" : 2050,
            "1744896" : 2000,
            "1761280" : 1850,
            "1777664" : 1772,
            "1794048" : 1757,
            "1810432" : 1705,
            "1826816" : 1581,
            "1843200" : 1625,
            "1859584" : 1429,
            "1875968" : 1451,
            "1892352" : 1477,
            "1908736" : 1261,
            "1925120" : 1218,
            "1941504" : 1113,
            "1957888" : 1114,
            "1974272" : 1074,
            "1990656" : 1043,
            "2007040" : 1020,
            "2023424" : 957,
            "2039808" : 879,
            "2056192" : 887,
            "2072576" : 838,
            "2088960" : 838,
            "2113536" : 1505,
            "2146304" : 1331,
            "2179072" : 1261,
            "2211840" : 1097,
            "2244608" : 1052,
            "2277376" : 903,
            "2310144" : 795,
            "2342912" : 777,
            "2375680" : 698,
            "2408448" : 607,
            "2441216" : 604,
            "2473984" : 512,
            "2506752" : 445,
            "2539520" : 419,
            "2572288" : 396,
            "2605056" : 304,
            "2637824" : 312,
            "2670592" : 311,
            "2703360" : 274,
            "2736128" : 256,
            "2768896" : 223,
            "2801664" : 196,
            "2834432" : 182,
            "2867200" : 154,
            "2899968" : 152,
            "2932736" : 146,
            "2965504" : 141,
            "2998272" : 150,
            "3031040" : 115,
            "3063808" : 98,
            "3096576" : 96,
            "3129344" : 91,
            "3162112" : 96,
            "3194880" : 85,
            "3227648" : 82,
            "3260416" : 67,
            "3293184" : 86,
            "3325952" : 60,
            "3358720" : 61,
            "3391488" : 58,
            "3424256" : 61,
            "3457024" : 45,
            "3489792" : 65,
            "3522560" : 57,
            "3555328" : 56,
            "3588096" : 58,
            "3620864" : 43,
            "3653632" : 38,
            "3686400" : 39,
            "3719168" : 40,
            "3751936" : 36,
            "3784704" : 31,
            "3817472" : 40,
            "3850240" : 41,
            "3883008" : 33,
            "3915776" : 37,
            "3948544" : 39,
            "3981312" : 25,
            "4014080" : 22,
            "4046848" : 27,
            "4079616" : 18,
            "4112384" : 18,
            "4145152" : 22,
            "4177920" : 16,
            "4227072" : 29,
            "4292608" : 29,
            "4358144" : 27,
            "4423680" : 37,
            "4489216" : 40,
            "4554752" : 43,
            "4620288" : 41,
            "4685824" : 33,
            "4751360" : 45,
            "4816896" : 53,
            "4882432" : 39,
            "4947968" : 38,
            "5013504" : 40,
            "5079040" : 42,
            "5144576" : 24,
            "5210112" : 21,
            "5275648" : 25,
            "5341184" : 22,
            "5406720" : 15,
            "5472256" : 15,
            "5537792" : 22,
            "5603328" : 21,
            "5668864" : 27,
            "5734400" : 28,
            "5799936" : 22,
            "5865472" : 22,
            "5931008" : 20,
            "5996544" : 23,
            "6062080" : 19,
            "6127616" : 15,
            "6193152" : 29,
            "6258688" : 15,
            "6324224" : 12,
            "6389760" : 11,
            "6455296" : 13,
            "6520832" : 19,
            "6586368" : 17,
            "6651904" : 9,
            "6717440" : 10,
            "6782976" : 13,
            "6848512" : 14,
            "6914048" : 7,
            "6979584" : 6,
            "7045120" : 4,
            "7110656" : 11,
            "7176192" : 7,
            "7241728" : 5,
            "7307264" : 11,
            "7372800" : 6,
            "7438336" : 11,
            "7503872" : 15,
            "7569408" : 8,
            "7634944" : 12,
            "7700480" : 8,
            "7766016" : 16,
            "7831552" : 16,
            "7897088" : 7,
            "7962624" : 5,
            "8028160" : 6,
            "8093696" : 4,
            "8159232" : 1,
            "8224768" : 3,
            "8290304" : 9,
            "8355840" : 2,
            "8454144" : 10,
            "8585216" : 8,
            "8716288" : 4,
            "8847360" : 17,
            "8978432" : 12,
            "9109504" : 17,
            "9240576" : 25,
            "9371648" : 18,
            "9502720" : 14,
            "9633792" : 3,
            "9764864" : 14,
            "9895936" : 16,
            "10027008" : 14,
            "10158080" : 18,
            "10289152" : 16,
            "10420224" : 10,
            "10551296" : 7,
            "10682368" : 10,
            "10813440" : 13,
            "10944512" : 4,
            "11075584" : 9,
            "11206656" : 9,
            "11337728" : 9,
            "11468800" : 11,
            "11599872" : 2,
            "11730944" : 18,
            "11862016" : 7,
            "11993088" : 15,
            "12124160" : 9,
            "12255232" : 10,
            "12386304" : 8,
            "12517376" : 11,
            "12648448" : 10,
            "12779520" : 14,
            "12910592" : 12,
            "13041664" : 11,
            "13172736" : 8,
            "13303808" : 19,
            "13434880" : 11,
            "13565952" : 6,
            "13697024" : 18,
            "13828096" : 4,
            "13959168" : 12,
            "14090240" : 6,
            "14221312" : 8,
            "14352384" : 8,
            "14483456" : 13,
            "14614528" : 14,
            "14745600" : 9,
            "14876672" : 12,
            "15007744" : 11,
            "15138816" : 9,
            "15269888" : 13,
            "15400960" : 8,
            "15532032" : 5,
            "15663104" : 9,
            "15794176" : 35,
            "15925248" : 16,
            "16056320" : 3,
            "16318464" : 5,
            "16449536" : 9,
            "16580608" : 5,
            "16711680" : 3,
            "16908288" : 18,
            "17170432" : 17,
            "17432576" : 19,
            "17694720" : 7,
            "17956864" : 20,
            "18219008" : 18,
            "18481152" : 20,
            "18743296" : 23,
            "19005440" : 13,
            "19267584" : 13,
            "19529728" : 15,
            "19791872" : 25,
            "20054016" : 19,
            "20316160" : 18,
            "20578304" : 6,
            "20840448" : 10,
            "21102592" : 28,
            "21364736" : 4,
            "21626880" : 1,
            "21889024" : 9,
            "22151168" : 11,
            "22413312" : 5,
            "22675456" : 8,
            "22937600" : 4,
            "23199744" : 9,
            "23461888" : 19,
            "23724032" : 4,
            "23986176" : 3,
            "24248320" : 8,
            "24510464" : 3,
            "24772608" : 1,
            "25034752" : 14,
            "25296896" : 4,
            "25559040" : 11,
            "25821184" : 5,
            "26607616" : 6,
            "26869760" : 1,
            "27394048" : 7,
            "27656192" : 4,
            "27918336" : 3,
            "28704768" : 2,
            "28966912" : 11,
            "29229056" : 1,
            "30015488" : 6,
            "30277632" : 1,
            "30539776" : 1,
            "30801920" : 6,
            "31064064" : 5,
            "31326208" : 4,
            "31850496" : 8,
            "32112640" : 11,
            "32374784" : 7,
            "32636928" : 2,
            "32899072" : 18,
            "33161216" : 8,
            "33423360" : 6,
            "33816576" : 14,
            "34340864" : 15,
            "34865152" : 7,
            "35389440" : 14,
            "35913728" : 7,
            "36438016" : 7,
            "36962304" : 9,
            "37486592" : 17,
            "38010880" : 16,
            "39059456" : 10,
            "39583744" : 7,
            "40108032" : 17,
            "40632320" : 11,
            "41156608" : 8,
            "41680896" : 30,
            "42205184" : 9,
            "42729472" : 7,
            "43253760" : 13,
            "43778048" : 19,
            "44302336" : 4,
            "44826624" : 5,
            "45350912" : 22,
            "45875200" : 41,
            "46399488" : 23,
            "46923776" : 21,
            "47448064" : 12,
            "47972352" : 14,
            "48496640" : 3,
            "49020928" : 12,
            "49545216" : 9,
            "50069504" : 26,
            "50593792" : 28,
            "51118080" : 24,
            "51642368" : 30,
            "52166656" : 11,
            "52690944" : 29,
            "53215232" : 22,
            "53739520" : 27,
            "54263808" : 14,
            "54788096" : 11,
            "55312384" : 12,
            "55836672" : 29,
            "56360960" : 32,
            "56885248" : 16,
            "57409536" : 19,
            "57933824" : 22,
            "58458112" : 11,
            "58982400" : 12,
            "59506688" : 16,
            "60030976" : 19,
            "60555264" : 21,
            "61079552" : 30,
            "61603840" : 10,
            "62128128" : 9,
            "63176704" : 7,
            "63700992" : 1,
            "64225280" : 10,
            "64749568" : 17,
            "65273856" : 12,
            "65798144" : 17,
            "66322432" : 13,
            "67633152" : 9,
            "68681728" : 19,
            "69730304" : 7,
            "70778880" : 7,
            "71827456" : 12,
            "72876032" : 8,
            "73924608" : 1,
            "74973184" : 7,
            "76021760" : 7,
            "77070336" : 7,
            "78118912" : 19,
            "79167488" : 26,
            "80216064" : 11,
            "82313216" : 7,
            "83361792" : 7,
            "84410368" : 1,
            "85458944" : 14,
            "86507520" : 20,
            "87556096" : 20,
            "88604672" : 13,
            "89653248" : 2,
            "90701824" : 9,
            "91750400" : 12,
            "92798976" : 1,
            "93847552" : 13,
            "94896128" : 2,
            "95944704" : 7,
            "96993280" : 26,
            "98041856" : 7,
            "99090432" : 7,
            "100139008" : 2,
            "101187584" : 19,
            "102236160" : 14,
            "104333312" : 14,
            "105381888" : 13,
            "106430464" : 13,
            "107479040" : 19,
            "108527616" : 33,
            "109576192" : 22,
            "110624768" : 19,
            "111673344" : 1,
            "113770496" : 13,
            "114819072" : 7,
            "117964800" : 7,
            "119013376" : 21,
            "121110528" : 2,
            "122159104" : 19,
            "123207680" : 14,
            "124256256" : 14,
            "125304832" : 8,
            "126353408" : 8,
            "127401984" : 19,
            "128450560" : 7,
            "129499136" : 21,
            "131596288" : 7,
            "135266304" : 28,
            "137363456" : 21,
            "139460608" : 7,
            "141557760" : 21,
            "143654912" : 7,
            "145752064" : 4,
            "147849216" : 21,
            "149946368" : 21,
            "152043520" : 24,
            "154140672" : 18,
            "156237824" : 10,
            "160432128" : 7,
            "162529280" : 7,
            "166723584" : 14,
            "168820736" : 7,
            "173015040" : 14,
            "175112192" : 14,
            "179306496" : 4,
            "181403648" : 10,
            "183500800" : 8,
            "185597952" : 6,
            "187695104" : 6,
            "189792256" : 15,
            "191889408" : 7,
            "193986560" : 7,
            "196083712" : 7,
            "198180864" : 21,
            "200278016" : 7,
            "202375168" : 7,
            "206569472" : 14,
            "210763776" : 14,
            "214958080" : 7,
            "217055232" : 7,
            "219152384" : 7,
            "221249536" : 10,
            "223346688" : 11,
            "225443840" : 14,
            "229638144" : 7,
            "231735296" : 7,
            "240123904" : 7,
            "244318208" : 7,
            "248512512" : 9,
            "250609664" : 5,
            "252706816" : 7,
            "254803968" : 4,
            "256901120" : 10,
            "258998272" : 7,
            "263192576" : 7,
            "270532608" : 21,
            "274726912" : 7,
            "278921216" : 24,
            "283115520" : 11,
            "287309824" : 14,
            "291504128" : 7,
            "299892736" : 14,
            "304087040" : 7,
            "308281344" : 7,
            "312475648" : 7,
            "316669952" : 8,
            "320864256" : 6,
            "325058560" : 2,
            "329252864" : 5,
            "341835776" : 7,
            "350224384" : 7,
            "358612992" : 7,
            "362807296" : 7,
            "367001600" : 7,
            "371195904" : 7,
            "375390208" : 14,
            "379584512" : 7,
            "383778816" : 14,
            "392167424" : 7,
            "400556032" : 7,
            "408944640" : 7,
            "421527552" : 7,
            "425721856" : 7,
            "434110464" : 7,
            "463470592" : 10,
            "467664896" : 4,
            "480247808" : 7,
            "488636416" : 7,
            "497025024" : 7,
            "549453824" : 7,
            "566231040" : 7,
            "792723456" : 7,
            "876609536" : 7,
            "1451229184" : 7
          }
        },
        "lat_ns" : {
          "min" : 281844,
          "max" : 1454266280,
          "mean" : 2242353.921147,
          "stddev" : 15791507.191704
        },
        "bw_min" : 3224,
        "bw_max" : 23599,
        "bw_agg" : 25.419732,
        "bw_mean" : 14492.297414,
        "bw_dev" : 4276.340172,
        "bw_samples" : 232,
        "iops_min" : 806,
        "iops_max" : 5899,
        "iops_mean" : 3622.956897,
        "iops_stddev" : 1069.087533,
        "iops_samples" : 232
      },
      "trim" : {
        "io_bytes" : 0,
        "io_kbytes" : 0,
        "bw" : 0,
        "iops" : 0.000000,
        "runtime" : 0,
        "total_ios" : 0,
        "short_ios" : 0,
        "drop_ios" : 0,
        "slat_ns" : {
          "min" : 0,
          "max" : 0,
          "mean" : 0.000000,
          "stddev" : 0.000000
        },
        "clat_ns" : {
          "min" : 0,
          "max" : 0,
          "mean" : 0.000000,
          "stddev" : 0.000000,
          "percentile" : {
            "1.000000" : 0,
            "5.000000" : 0,
            "10.000000" : 0,
            "20.000000" : 0,
            "30.000000" : 0,
            "40.000000" : 0,
            "50.000000" : 0,
            "60.000000" : 0,
            "70.000000" : 0,
            "80.000000" : 0,
            "90.000000" : 0,
            "95.000000" : 0,
            "99.000000" : 0,
            "99.500000" : 0,
            "99.900000" : 0,
            "99.950000" : 0,
            "99.990000" : 0,
            "0.00" : 0,
            "0.00" : 0,
            "0.00" : 0
          },
          "bins" : {

          }
        },
        "lat_ns" : {
          "min" : 0,
          "max" : 0,
          "mean" : 0.000000,
          "stddev" : 0.000000
        },
        "bw_min" : 0,
        "bw_max" : 0,
        "bw_agg" : 0.000000,
        "bw_mean" : 0.000000,
        "bw_dev" : 0.000000,
        "bw_samples" : 0,
        "iops_min" : 0,
        "iops_max" : 0,
        "iops_mean" : 0.000000,
        "iops_stddev" : 0.000000,
        "iops_samples" : 0
      },
      "usr_cpu" : 1.732500,
      "sys_cpu" : 5.190833,
      "ctx" : 470284,
      "majf" : 0,
      "minf" : 42,
      "iodepth_level" : {
        "1" : 0.100000,
        "2" : 0.100000,
        "4" : 0.100000,
        "8" : 99.993452,
        "16" : 0.000000,
        "32" : 0.000000,
        ">=64" : 0.000000
      },
      "latency_ns" : {
        "2" : 0.000000,
        "4" : 0.000000,
        "10" : 0.000000,
        "20" : 0.000000,
        "50" : 0.000000,
        "100" : 0.000000,
        "250" : 0.000000,
        "500" : 0.000000,
        "750" : 0.000000,
        "1000" : 0.000000
      },
      "latency_us" : {
        "2" : 0.000000,
        "4" : 0.010000,
        "10" : 0.010000,
        "20" : 0.000000,
        "50" : 0.000000,
        "100" : 0.000000,
        "250" : 0.000000,
        "500" : 3.889562,
        "750" : 22.049504,
        "1000" : 21.763960
      },
      "latency_ms" : {
        "2" : 45.904641,
        "4" : 5.220226,
        "10" : 0.351024,
        "20" : 0.174927,
        "50" : 0.171653,
        "100" : 0.198547,
        "250" : 0.189894,
        "500" : 0.076940,
        "750" : 0.010000,
        "1000" : 0.010000,
        "2000" : 0.010000,
        ">=2000" : 0.000000
      },
      "latency_depth" : 8,
      "latency_target" : 0,
      "latency_percentile" : 100.000000,
      "latency_window" : 0
    }
  ]
}
